stenotype/__init__.py
stenotype/backend/__init__.py
stenotype/backend/elements.py
stenotype/backend/grammar.py
stenotype/backend/steno.py
stenotype/backend/typing.py
stenotype/cli.py
stenotype/util.py
stenotype-0.2.0.dist-info/entry_points.txt
stenotype-0.2.0.dist-info/LICENSE
stenotype-0.2.0.dist-info/WHEEL
stenotype-0.2.0.dist-info/METADATA
stenotype-0.2.0.dist-info/RECORD
