Metadata-Version: 2.1
Name: stenotype
Version: 0.2.0
Summary: Support for shorthand type annotations.
Home-page: https://github.com/a-recknagel/stenotype
License: MIT
Keywords: typing,annotation
Author: Arne Recknagel
Author-email: arne.recknagel@hotmail.com
Requires-Python: >=3.6,<4.0
Classifier: License :: OSI Approved :: MIT License
Classifier: Programming Language :: Python :: 3
Classifier: Programming Language :: Python :: 3.6
Classifier: Programming Language :: Python :: 3.7
Classifier: Programming Language :: Python :: 3.8
Requires-Dist: click (>=7.0,<8.0)
Project-URL: Repository, https://github.com/a-recknagel/stenotype
